{
  "_id": "Y35rQsh1GWrH1t5m",
  "name": "Drums of Panic",
  "type": "item",
  "img": "icons/tools/instruments/drum-brown-red.webp",
  "effects": [],
  "folder": "bUDTw9Q5QNa0VZwi",
  "sort": 6800000,
  "flags": {},
  "system": {
    "description": "<p>Large war drums that induce panic in those who hear their sound.</p><ul><li><p><strong>Range</strong>: Creatures up to 240’ away, are affected, when the drums are played. Those within 10’ of the drums are not affected.</p></li><li><p><strong>Affected creatures</strong>: Are afflicted by the drums’ enchantment of fear: they must <em><strong>save versus spells</strong></em> or make a morale check with a –2 penalty (if the optional morale rules are being used—@UUID[Compendium.ose-advancedfantasytome.rules.JournalEntry.u9gtXY21VnjrwwkH.JournalEntryPage.4dfEUllNr02Vm7ze]{see Morale}).</p></li><li><p><strong>Effects</strong>: Creatures that fail the saving throw or morale check flee from the sound of the drums at full running speed for 30 rounds.</p></li></ul>",
    "autoTags": [],
    "manualTags": [],
    "quantity": {
      "value": 1,
      "max": 1
    },
    "weight": 0,
    "cost": 0,
    "containerId": "",
    "treasure": false,
    "isContainer": false,
    "tags": [
      {
        "title": "Magic",
        "value": "Magic"
      }
    ]
  },
  "ownership": {
    "default": 0
  },
  "_stats": {
    "systemId": "ose",
    "systemVersion": "2.1.9",
    "coreVersion": "13.350",
    "createdTime": 1687339326487,
    "modifiedTime": 1761430085982,
    "lastModifiedBy": "osebuilder000000",
    "duplicateSource": null,
    "exportSource": null
  },
  "_key": "!items!Y35rQsh1GWrH1t5m"
}
