{
  "name": "C1.1 Cure Light Wounds",
  "type": "spell",
  "flags": {},
  "img": "/systems/ose/assets/default/spell.png",
  "effects": [],
  "_id": "Fk7WWaD2PGeu9vY0",
  "_stats": {
    "coreVersion": "13.345",
    "systemId": null,
    "systemVersion": null,
    "createdTime": null,
    "modifiedTime": 1751863156929,
    "lastModifiedBy": "osebuilder000000",
    "duplicateSource": null,
    "exportSource": null
  },
  "ownership": {
    "default": 0
  },
  "system": {
    "description": "<p style=\"box-sizing: border-box; user-select: text; color: #191813;\">This spell has two uses</p>\n<ol style=\"box-sizing: border-box; user-select: text; color: #191813;\">\n<li style=\"box-sizing: border-box; user-select: text;\"><strong style=\"box-sizing: border-box; user-select: text;\">Healing a living subject:</strong>&nbsp;Restores 1d6+1 hit points of damage. This cannot grant more hit points than the subject&rsquo;s normal maximum.</li>\n<li style=\"box-sizing: border-box; user-select: text;\"><strong style=\"box-sizing: border-box; user-select: text;\">Curing paralysis:</strong>&nbsp;Paralysing effects are negated.</li>\n</ol>\n<h2 style=\"box-sizing: border-box; user-select: text; color: #191813;\"><span style=\"box-sizing: border-box; user-select: text;\">Reversed</span></h2>\n<p style=\"box-sizing: border-box; user-select: text; color: #191813;\"><span style=\"box-sizing: border-box; user-select: text;\">See </span><strong style=\"box-sizing: border-box; user-select: text;\">Cause Light Wounds</strong><span style=\"box-sizing: border-box; user-select: text;\">.</span></p>",
    "autoTags": [],
    "manualTags": [],
    "save": "",
    "lvl": 1,
    "class": "Cleric",
    "duration": "Instant",
    "range": "The caster or a creature touched",
    "roll": "1d6+1",
    "memorized": 0,
    "cast": 0
  },
  "folder": "ZqMuAcZCeYDB8FsT",
  "sort": 100000,
  "_key": "!items!Fk7WWaD2PGeu9vY0"
}
