{
  "_id": "00FjkN68MifyJTKx",
  "name": "Potion of Clairvoyance",
  "type": "item",
  "img": "icons/consumables/potions/bottle-conical-bubbling-blue.webp",
  "effects": [],
  "folder": "IHA5DDN3y3qLHr52",
  "sort": 0,
  "flags": {},
  "system": {
    "description": "<p>Enables the character to see through the eyes of another creature.</p><ul><li><p><strong>Range:</strong> The other creature must be within 60’.</p></li><li><p><strong>Obstructions</strong>: Lead blocks the effect.</p></li></ul>",
    "autoTags": [],
    "manualTags": [],
    "quantity": {
      "value": 1,
      "max": 1
    },
    "weight": 10,
    "cost": 0,
    "containerId": "",
    "treasure": false,
    "isContainer": false,
    "tags": [
      {
        "title": "Magic",
        "value": "Magic"
      }
    ],
    "equipped": false,
    "itemslots": 0
  },
  "ownership": {
    "default": 0
  },
  "_stats": {
    "systemId": "ose",
    "systemVersion": "2.1.9",
    "coreVersion": "13.350",
    "createdTime": 1687339326487,
    "modifiedTime": 1761442172025,
    "lastModifiedBy": "osebuilder000000",
    "duplicateSource": null,
    "exportSource": null
  },
  "_key": "!items!00FjkN68MifyJTKx"
}
